{"pokemon": {"weight": 34, "sprites": {"front_default": "http://pokeapi.co/media/sprites/pokemon/412.png", "front_female": null, "back_shiny": "http://pokeapi.co/media/sprites/pokemon/back/shiny/412.png", "back_default": "http://pokeapi.co/media/sprites/pokemon/back/412.png", "back_shiny_female": null, "back_female": null, "front_shiny": "http://pokeapi.co/media/sprites/pokemon/shiny/412.png", "front_shiny_female": null}, "species": {"url": "https://pokeapi.co/api/v2/pokemon-species/412/", "name": "burmy"}, "forms": [{"url": "https://pokeapi.co/api/v2/pokemon-form/10035/", "name": "burmy-trash"}, {"url": "https://pokeapi.co/api/v2/pokemon-form/10034/", "name": "burmy-sandy"}, {"url": "https://pokeapi.co/api/v2/pokemon-form/412/", "name": "burmy-plant"}], "base_experience": 45, "abilities": [{"ability": {"url": "https://pokeapi.co/api/v2/ability/142/", "name": "overcoat"}, "is_hidden": true, "slot": 3}, {"ability": {"url": "https://pokeapi.co/api/v2/ability/61/", "name": "shed-skin"}, "is_hidden": false, "slot": 1}], "is_default": true, "id": 412, "stats": [{"base_stat": 36, "effort": 0, "stat": {"url": "https://pokeapi.co/api/v2/stat/6/", "name": "speed"}}, {"base_stat": 45, "effort": 1, "stat": {"url": "https://pokeapi.co/api/v2/stat/5/", "name": "special-defense"}}, {"base_stat": 29, "effort": 0, "stat": {"url": "https://pokeapi.co/api/v2/stat/4/", "name": "special-attack"}}, {"base_stat": 45, "effort": 0, "stat": {"url": "https://pokeapi.co/api/v2/stat/3/", "name": "defense"}}, {"base_stat": 29, "effort": 0, "stat": {"url": "https://pokeapi.co/api/v2/stat/2/", "name": "attack"}}, {"base_stat": 40, "effort": 0, "stat": {"url": "https://pokeapi.co/api/v2/stat/1/", "name": "hp"}}], "moves": [{"move": {"url": "https://pokeapi.co/api/v2/move/33/", "name": "tackle"}, "version_group_details": [{"move_learn_method": {"url": "https://pokeapi.co/api/v2/move-learn-method/1/", "name": "level-up"}, "level_learned_at": 10, "version_group": {"url": "https://pokeapi.co/api/v2/version-group/16/", "name": "omega-ruby-alpha-sapphire"}}, {"move_learn_method": {"url": "https://pokeapi.co/api/v2/move-learn-method/1/", "name": "level-up"}, "level_learned_at": 10, "version_group": {"url": "https://pokeapi.co/api/v2/version-group/15/", "name": "x-y"}}, {"move_learn_method": {"url": "https://pokeapi.co/api/v2/move-learn-method/1/", "name": "level-up"}, "level_learned_at": 10, "version_group": {"url": "https://pokeapi.co/api/v2/version-group/14/", "name": "black-2-white-2"}}, {"move_learn_method": {"url": "https://pokeapi.co/api/v2/move-learn-method/1/", "name": "level-up"}, "level_learned_at": 10, "version_group": {"url": "https://pokeapi.co/api/v2/version-group/11/", "name": "black-white"}}, {"move_learn_method": {"url": "https://pokeapi.co/api/v2/move-learn-method/1/", "name": "level-up"}, "level_learned_at": 10, "version_group": {"url": "https://pokeapi.co/api/v2/version-group/10/", "name": "heartgold-soulsilver"}}, {"move_learn_method": {"url": "https://pokeapi.co/api/v2/move-learn-method/1/", "name": "level-up"}, "level_learned_at": 10, "version_group": {"url": "https://pokeapi.co/api/v2/version-group/9/", "name": "platinum"}}, {"move_learn_method": {"url": "https://pokeapi.co/api/v2/move-learn-method/1/", "name": "level-up"}, "level_learned_at": 10, "version_group": {"url": "https://pokeapi.co/api/v2/version-group/8/", "name": "diamond-pearl"}}]}, {"move": {"url": "https://pokeapi.co/api/v2/move/81/", "name": "string-shot"}, "version_group_details": [{"move_learn_method": {"url": "https://pokeapi.co/api/v2/move-learn-method/3/", "name": "tutor"}, "level_learned_at": 0, "version_group": {"url": "https://pokeapi.co/api/v2/version-group/10/", "name": "heartgold-soulsilver"}}]}, {"move": {"url": "https://pokeapi.co/api/v2/move/173/", "name": "snore"}, "version_group_details": [{"move_learn_method": {"url": "https://pokeapi.co/api/v2/move-learn-method/3/", "name": "tutor"}, "level_learned_at": 0, "version_group": {"url": "https://pokeapi.co/api/v2/version-group/16/", "name": "omega-ruby-alpha-sapphire"}}, {"move_learn_method": {"url": "https://pokeapi.co/api/v2/move-learn-method/3/", "name": "tutor"}, "level_learned_at": 0, "version_group": {"url": "https://pokeapi.co/api/v2/version-group/14/", "name": "black-2-white-2"}}, {"move_learn_method": {"url": "https://pokeapi.co/api/v2/move-learn-method/3/", "name": "tutor"}, "level_learned_at": 0, "version_group": {"url": "https://pokeapi.co/api/v2/version-group/10/", "name": "heartgold-soulsilver"}}, {"move_learn_method": {"url": "https://pokeapi.co/api/v2/move-learn-method/3/", "name": "tutor"}, "level_learned_at": 0, "version_group": {"url": "https://pokeapi.co/api/v2/version-group/9/", "name": "platinum"}}]}, {"move": {"url": "https://pokeapi.co/api/v2/move/182/", "name": "protect"}, "version_group_details": [{"move_learn_method": {"url": "https://pokeapi.co/api/v2/move-learn-method/4/", "name": "machine"}, "level_learned_at": 0, "version_group": {"url": "https://pokeapi.co/api/v2/version-group/16/", "name": "omega-ruby-alpha-sapphire"}}, {"move_learn_method": {"url": "https://pokeapi.co/api/v2/move-learn-method/1/", "name": "level-up"}, "level_learned_at": 1, "version_group": {"url": "https://pokeapi.co/api/v2/version-group/16/", "name": "omega-ruby-alpha-sapphire"}}, {"move_learn_method": {"url": "https://pokeapi.co/api/v2/move-learn-method/4/", "name": "machine"}, "level_learned_at": 0, "version_group": {"url": "https://pokeapi.co/api/v2/version-group/15/", "name": "x-y"}}, {"move_learn_method": {"url": "https://pokeapi.co/api/v2/move-learn-method/1/", "name": "level-up"}, "level_learned_at": 1, "version_group": {"url": "https://pokeapi.co/api/v2/version-group/15/", "name": "x-y"}}, {"move_learn_method": {"url": "https://pokeapi.co/api/v2/move-learn-method/1/", "name": "level-up"}, "level_learned_at": 1, "version_group": {"url": "https://pokeapi.co/api/v2/version-group/14/", "name": "black-2-white-2"}}, {"move_learn_method": {"url": "https://pokeapi.co/api/v2/move-learn-method/1/", "name": "level-up"}, "level_learned_at": 1, "version_group": {"url": "https://pokeapi.co/api/v2/version-group/11/", "name": "black-white"}}, {"move_learn_method": {"url": "https://pokeapi.co/api/v2/move-learn-method/1/", "name": "level-up"}, "level_learned_at": 1, "version_group": {"url": "https://pokeapi.co/api/v2/version-group/10/", "name": "heartgold-soulsilver"}}, {"move_learn_method": {"url": "https://pokeapi.co/api/v2/move-learn-method/1/", "name": "level-up"}, "level_learned_at": 1, "version_group": {"url": "https://pokeapi.co/api/v2/version-group/9/", "name": "platinum"}}, {"move_learn_method": {"url": "https://pokeapi.co/api/v2/move-learn-method/1/", "name": "level-up"}, "level_learned_at": 1, "version_group": {"url": "https://pokeapi.co/api/v2/version-group/8/", "name": "diamond-pearl"}}]}, {"move": {"url": "https://pokeapi.co/api/v2/move/237/", "name": "hidden-power"}, "version_group_details": [{"move_learn_method": {"url": "https://pokeapi.co/api/v2/move-learn-method/4/", "name": "machine"}, "level_learned_at": 0, "version_group": {"url": "https://pokeapi.co/api/v2/version-group/16/", "name": "omega-ruby-alpha-sapphire"}}, {"move_learn_method": {"url": "https://pokeapi.co/api/v2/move-learn-method/1/", "name": "level-up"}, "level_learned_at": 20, "version_group": {"url": "https://pokeapi.co/api/v2/version-group/16/", "name": "omega-ruby-alpha-sapphire"}}, {"move_learn_method": {"url": "https://pokeapi.co/api/v2/move-learn-method/4/", "name": "machine"}, "level_learned_at": 0, "version_group": {"url": "https://pokeapi.co/api/v2/version-group/15/", "name": "x-y"}}, {"move_learn_method": {"url": "https://pokeapi.co/api/v2/move-learn-method/1/", "name": "level-up"}, "level_learned_at": 20, "version_group": {"url": "https://pokeapi.co/api/v2/version-group/15/", "name": "x-y"}}, {"move_learn_method": {"url": "https://pokeapi.co/api/v2/move-learn-method/1/", "name": "level-up"}, "level_learned_at": 20, "version_group": {"url": "https://pokeapi.co/api/v2/version-group/14/", "name": "black-2-white-2"}}, {"move_learn_method": {"url": "https://pokeapi.co/api/v2/move-learn-method/1/", "name": "level-up"}, "level_learned_at": 20, "version_group": {"url": "https://pokeapi.co/api/v2/version-group/11/", "name": "black-white"}}, {"move_learn_method": {"url": "https://pokeapi.co/api/v2/move-learn-method/1/", "name": "level-up"}, "level_learned_at": 20, "version_group": {"url": "https://pokeapi.co/api/v2/version-group/10/", "name": "heartgold-soulsilver"}}, {"move_learn_method": {"url": "https://pokeapi.co/api/v2/move-learn-method/1/", "name": "level-up"}, "level_learned_at": 20, "version_group": {"url": "https://pokeapi.co/api/v2/version-group/9/", "name": "platinum"}}, {"move_learn_method": {"url": "https://pokeapi.co/api/v2/move-learn-method/1/", "name": "level-up"}, "level_learned_at": 20, "version_group": {"url": "https://pokeapi.co/api/v2/version-group/8/", "name": "diamond-pearl"}}]}, {"move": {"url": "https://pokeapi.co/api/v2/move/450/", "name": "bug-bite"}, "version_group_details": [{"move_learn_method": {"url": "https://pokeapi.co/api/v2/move-learn-method/3/", "name": "tutor"}, "level_learned_at": 0, "version_group": {"url": "https://pokeapi.co/api/v2/version-group/16/", "name": "omega-ruby-alpha-sapphire"}}, {"move_learn_method": {"url": "https://pokeapi.co/api/v2/move-learn-method/1/", "name": "level-up"}, "level_learned_at": 15, "version_group": {"url": "https://pokeapi.co/api/v2/version-group/16/", "name": "omega-ruby-alpha-sapphire"}}, {"move_learn_method": {"url": "https://pokeapi.co/api/v2/move-learn-method/1/", "name": "level-up"}, "level_learned_at": 15, "version_group": {"url": "https://pokeapi.co/api/v2/version-group/15/", "name": "x-y"}}, {"move_learn_method": {"url": "https://pokeapi.co/api/v2/move-learn-method/3/", "name": "tutor"}, "level_learned_at": 0, "version_group": {"url": "https://pokeapi.co/api/v2/version-group/14/", "name": "black-2-white-2"}}, {"move_learn_method": {"url": "https://pokeapi.co/api/v2/move-learn-method/1/", "name": "level-up"}, "level_learned_at": 15, "version_group": {"url": "https://pokeapi.co/api/v2/version-group/14/", "name": "black-2-white-2"}}, {"move_learn_method": {"url": "https://pokeapi.co/api/v2/move-learn-method/1/", "name": "level-up"}, "level_learned_at": 15, "version_group": {"url": "https://pokeapi.co/api/v2/version-group/11/", "name": "black-white"}}, {"move_learn_method": {"url": "https://pokeapi.co/api/v2/move-learn-method/3/", "name": "tutor"}, "level_learned_at": 0, "version_group": {"url": "https://pokeapi.co/api/v2/version-group/10/", "name": "heartgold-soulsilver"}}, {"move_learn_method": {"url": "https://pokeapi.co/api/v2/move-learn-method/1/", "name": "level-up"}, "level_learned_at": 15, "version_group": {"url": "https://pokeapi.co/api/v2/version-group/10/", "name": "heartgold-soulsilver"}}, {"move_learn_method": {"url": "https://pokeapi.co/api/v2/move-learn-method/1/", "name": "level-up"}, "level_learned_at": 15, "version_group": {"url": "https://pokeapi.co/api/v2/version-group/9/", "name": "platinum"}}]}, {"move": {"url": "https://pokeapi.co/api/v2/move/527/", "name": "electroweb"}, "version_group_details": [{"move_learn_method": {"url": "https://pokeapi.co/api/v2/move-learn-method/3/", "name": "tutor"}, "level_learned_at": 0, "version_group": {"url": "https://pokeapi.co/api/v2/version-group/16/", "name": "omega-ruby-alpha-sapphire"}}, {"move_learn_method": {"url": "https://pokeapi.co/api/v2/move-learn-method/3/", "name": "tutor"}, "level_learned_at": 0, "version_group": {"url": "https://pokeapi.co/api/v2/version-group/14/", "name": "black-2-white-2"}}]}], "location_area_encounters": "/api/v2/pokemon/412/encounters", "held_items": [], "order": 496, "types": [{"type": {"url": "https://pokeapi.co/api/v2/type/7/", "name": "bug"}, "slot": 1}], "height": 2, "game_indices": [{"version": {"url": "https://pokeapi.co/api/v2/version/22/", "name": "white-2"}, "game_index": 412}, {"version": {"url": "https://pokeapi.co/api/v2/version/21/", "name": "black-2"}, "game_index": 412}, {"version": {"url": "https://pokeapi.co/api/v2/version/18/", "name": "white"}, "game_index": 412}, {"version": {"url": "https://pokeapi.co/api/v2/version/17/", "name": "black"}, "game_index": 412}, {"version": {"url": "https://pokeapi.co/api/v2/version/16/", "name": "soulsilver"}, "game_index": 412}, {"version": {"url": "https://pokeapi.co/api/v2/version/15/", "name": "heartgold"}, "game_index": 412}, {"version": {"url": "https://pokeapi.co/api/v2/version/14/", "name": "platinum"}, "game_index": 412}, {"version": {"url": "https://pokeapi.co/api/v2/version/13/", "name": "pearl"}, "game_index": 412}, {"version": {"url": "https://pokeapi.co/api/v2/version/12/", "name": "diamond"}, "game_index": 412}], "name": "burmy"}, "species": {"color": {"url": "https://pokeapi.co/api/v2/pokemon-color/4/", "name": "gray"}, "form_descriptions": [{"language": {"url": "https://pokeapi.co/api/v2/language/9/", "name": "en"}, "description": "Forms only affect appearance, although they become permanent upon evolution.  Wild and newly-hatched Burmy are always in a Plant Cloak.  Burmy's cloak changes to match the terrain after a battle it participated in: Plant Cloak by default; Sandy Cloak in sandy or rocky areas, such as beaches, caves, and trails; and Trash Cloak in buildings."}], "evolution_chain": {"url": "https://pokeapi.co/api/v2/evolution-chain/213/"}, "pokedex_numbers": [{"pokedex": {"url": "https://pokeapi.co/api/v2/pokedex/12/", "name": "kalos-central"}, "entry_number": 44}, {"pokedex": {"url": "https://pokeapi.co/api/v2/pokedex/6/", "name": "extended-sinnoh"}, "entry_number": 45}, {"pokedex": {"url": "https://pokeapi.co/api/v2/pokedex/5/", "name": "original-sinnoh"}, "entry_number": 45}, {"pokedex": {"url": "https://pokeapi.co/api/v2/pokedex/1/", "name": "national"}, "entry_number": 412}], "pal_park_encounters": [{"base_score": 50, "area": {"url": "https://pokeapi.co/api/v2/pal-park-area/1/", "name": "forest"}, "rate": 30}], "shape": {"url": "https://pokeapi.co/api/v2/pokemon-shape/2/", "name": "squiggle"}, "varieties": [{"is_default": true, "pokemon": {"url": "https://pokeapi.co/api/v2/pokemon/412/", "name": "burmy"}}], "is_baby": false, "has_gender_differences": false, "flavor_text_entries": [{"language": {"url": "https://pokeapi.co/api/v2/language/11/", "name": "ja-kanji"}, "version": {"url": "https://pokeapi.co/api/v2/version/26/", "name": "alpha-sapphire"}, "flavor_text": "\u6226\u3044\u3067\u3000\u30df\u30ce\u304c\u3000\u58ca\u308c\u3066\u3057\u307e\u3046\u3068\n\u8fd1\u304f\u306b\u3042\u308b\u3000\u6750\u6599\u3067\n\u30df\u30ce\u3092\u3000\u3059\u3050\u306b\u3000\u4f5c\u308a\u76f4\u3059\u3002"}, {"language": {"url": "https://pokeapi.co/api/v2/language/9/", "name": "en"}, "version": {"url": "https://pokeapi.co/api/v2/version/26/", "name": "alpha-sapphire"}, "flavor_text": "If its cloak is broken in battle, it quickly remakes\nthe cloak with materials nearby."}, {"language": {"url": "https://pokeapi.co/api/v2/language/8/", "name": "it"}, "version": {"url": "https://pokeapi.co/api/v2/version/26/", "name": "alpha-sapphire"}, "flavor_text": "Se il suo manto si rompe mentre lotta, lo rif\u00e0 velocemente con\nci\u00f2 che trova attorno a s\u00e9."}, {"language": {"url": "https://pokeapi.co/api/v2/language/7/", "name": "es"}, "version": {"url": "https://pokeapi.co/api/v2/version/26/", "name": "alpha-sapphire"}, "flavor_text": "Si su caparaz\u00f3n se rompe en combate, lo rehace r\u00e1pidamente\ncon lo que tenga a mano."}, {"language": {"url": "https://pokeapi.co/api/v2/language/6/", "name": "de"}, "version": {"url": "https://pokeapi.co/api/v2/version/26/", "name": "alpha-sapphire"}, "flavor_text": "Wird sein Umhang im Kampf zerst\u00f6rt, macht es sich schnell\naus dem, was es findet, einen neuen."}, {"language": {"url": "https://pokeapi.co/api/v2/language/5/", "name": "fr"}, "version": {"url": "https://pokeapi.co/api/v2/version/26/", "name": "alpha-sapphire"}, "flavor_text": "S\u2019il perd sa cape au combat, il en tisse rapidement\nune nouvelle avec ce qui lui tombe sous la main."}, {"language": {"url": "https://pokeapi.co/api/v2/language/3/", "name": "ko"}, "version": {"url": "https://pokeapi.co/api/v2/version/26/", "name": "alpha-sapphire"}, "flavor_text": "\uc2f8\uc6c0\uc73c\ub85c \ub3c4\ub871\uc774\uac00 \ubd80\uc11c\uc838 \ubc84\ub9ac\uba74\n\uac00\uae4c\uc774 \uc788\ub294 \uc7ac\ub8cc\ub85c\n\ub3c4\ub871\uc774\ub97c \ubc14\ub85c \ub9cc\ub4e4\uc5b4 \uace0\uce5c\ub2e4."}, {"language": {"url": "https://pokeapi.co/api/v2/language/1/", "name": "ja"}, "version": {"url": "https://pokeapi.co/api/v2/version/26/", "name": "alpha-sapphire"}, "flavor_text": "\u305f\u305f\u304b\u3044\u3067\u3000\u30df\u30ce\u304c\u3000\u3053\u308f\u308c\u3066\u3057\u307e\u3046\u3068\n\u3061\u304b\u304f\u306b\u3042\u308b\u3000\u3056\u3044\u308a\u3087\u3046\u3067\n\u30df\u30ce\u3092\u3000\u3059\u3050\u306b\u3000\u3064\u304f\u308a\u306a\u304a\u3059\u3002"}, {"language": {"url": "https://pokeapi.co/api/v2/language/11/", "name": "ja-kanji"}, "version": {"url": "https://pokeapi.co/api/v2/version/25/", "name": "omega-ruby"}, "flavor_text": "\u51b7\u305f\u3044\u3000\u6728\u67af\u3089\u3057\u3092\u3000\u9632\u3050\u305f\u3081\n\u5c0f\u679d\u3084\u3000\u843d\u3061\u8449\u3092\u3000\u6750\u6599\u306b\n\u30df\u30ce\u3092\u3000\u4f5c\u308a\u3000\u4f53\u3092\u3000\u8986\u3046\u3002"}, {"language": {"url": "https://pokeapi.co/api/v2/language/9/", "name": "en"}, "version": {"url": "https://pokeapi.co/api/v2/version/25/", "name": "omega-ruby"}, "flavor_text": "To shelter itself from cold, wintry winds, it covers\nitself with a cloak made of twigs and leaves."}, {"language": {"url": "https://pokeapi.co/api/v2/language/8/", "name": "it"}, "version": {"url": "https://pokeapi.co/api/v2/version/25/", "name": "omega-ruby"}, "flavor_text": "Per ripararsi dal freddo e dai venti invernali si copre con un\nmanto fatto di rami e foglie."}, {"language": {"url": "https://pokeapi.co/api/v2/language/7/", "name": "es"}, "version": {"url": "https://pokeapi.co/api/v2/version/25/", "name": "omega-ruby"}, "flavor_text": "Para protegerse de los vientos fr\u00edos invernales, se cubre con\nun caparaz\u00f3n de ramas y hojas."}, {"language": {"url": "https://pokeapi.co/api/v2/language/6/", "name": "de"}, "version": {"url": "https://pokeapi.co/api/v2/version/25/", "name": "omega-ruby"}, "flavor_text": "Um sich vor dem eisigen Winterwind zu sch\u00fctzen, legt es sich\nunter einen Umhang aus \u00c4sten und Laub."}, {"language": {"url": "https://pokeapi.co/api/v2/language/5/", "name": "fr"}, "version": {"url": "https://pokeapi.co/api/v2/version/25/", "name": "omega-ruby"}, "flavor_text": "Pour se prot\u00e9ger des vents glac\u00e9s de l\u2019hiver, il s\u2019est tiss\u00e9\nune cape de feuilles et de brindilles."}, {"language": {"url": "https://pokeapi.co/api/v2/language/3/", "name": "ko"}, "version": {"url": "https://pokeapi.co/api/v2/version/25/", "name": "omega-ruby"}, "flavor_text": "\ucc28\uac00\uc6b4 \ucd08\uaca8\uc6b8 \ubc14\ub78c\uc744 \ub9c9\uc73c\ub824\uace0\n\uc791\uc740 \uac00\uc9c0\ub098 \ub099\uc5fd\uc744 \uc7ac\ub8cc\ub85c\n\ub3c4\ub871\uc774\ub97c \ub9cc\ub4e4\uc5b4 \ubab8\uc744 \uac10\uc2fc\ub2e4."}, {"language": {"url": "https://pokeapi.co/api/v2/language/1/", "name": "ja"}, "version": {"url": "https://pokeapi.co/api/v2/version/25/", "name": "omega-ruby"}, "flavor_text": "\u3064\u3081\u305f\u3044\u3000\u3053\u304c\u3089\u3057\u3092\u3000\u3075\u305b\u3050\u305f\u3081\n\u3053\u3048\u3060\u3084\u3000\u304a\u3061\u3070\u3092\u3000\u3056\u3044\u308a\u3087\u3046\u306b\n\u30df\u30ce\u3092\u3000\u3064\u304f\u308a\u3000\u304b\u3089\u3060\u3092\u3000\u304a\u304a\u3046\u3002"}, {"language": {"url": "https://pokeapi.co/api/v2/language/11/", "name": "ja-kanji"}, "version": {"url": "https://pokeapi.co/api/v2/version/24/", "name": "y"}, "flavor_text": "\u6226\u3044\u3067\u3000\u30df\u30ce\u304c\u3000\u58ca\u308c\u3066\u3057\u307e\u3046\u3068\n\u8fd1\u304f\u306b\u3042\u308b\u3000\u6750\u6599\u3067\n\u30df\u30ce\u3092\u3000\u3059\u3050\u306b\u3000\u4f5c\u308a\u76f4\u3059\u3002"}, {"language": {"url": "https://pokeapi.co/api/v2/language/9/", "name": "en"}, "version": {"url": "https://pokeapi.co/api/v2/version/24/", "name": "y"}, "flavor_text": "If its cloak is broken in battle, it quickly remakes\nthe cloak with materials nearby."}, {"language": {"url": "https://pokeapi.co/api/v2/language/8/", "name": "it"}, "version": {"url": "https://pokeapi.co/api/v2/version/24/", "name": "y"}, "flavor_text": "Se il suo manto si rompe mentre lotta, lo rif\u00e0\nvelocemente con ci\u00f2 che trova attorno a s\u00e9."}, {"language": {"url": "https://pokeapi.co/api/v2/language/7/", "name": "es"}, "version": {"url": "https://pokeapi.co/api/v2/version/24/", "name": "y"}, "flavor_text": "Si su caparaz\u00f3n se rompe en combate, lo rehace\nr\u00e1pidamente con lo que tenga a mano."}, {"language": {"url": "https://pokeapi.co/api/v2/language/6/", "name": "de"}, "version": {"url": "https://pokeapi.co/api/v2/version/24/", "name": "y"}, "flavor_text": "Wird sein Umhang im Kampf zerst\u00f6rt, macht es sich\nschnell aus dem, was es findet, einen neuen."}, {"language": {"url": "https://pokeapi.co/api/v2/language/5/", "name": "fr"}, "version": {"url": "https://pokeapi.co/api/v2/version/24/", "name": "y"}, "flavor_text": "S\u2019il perd sa cape au combat, il en tisse rapidement\nune nouvelle avec ce qui lui tombe sous la main."}, {"language": {"url": "https://pokeapi.co/api/v2/language/3/", "name": "ko"}, "version": {"url": "https://pokeapi.co/api/v2/version/24/", "name": "y"}, "flavor_text": "\uc2f8\uc6c0\uc73c\ub85c \ub3c4\ub871\uc774\uac00 \ubd80\uc11c\uc838 \ubc84\ub9ac\uba74\n\uac00\uae4c\uc774 \uc788\ub294 \uc7ac\ub8cc\ub85c\n\ub3c4\ub871\uc774\ub97c \ubc14\ub85c \ub9cc\ub4e4\uc5b4 \uace0\uce5c\ub2e4."}, {"language": {"url": "https://pokeapi.co/api/v2/language/1/", "name": "ja"}, "version": {"url": "https://pokeapi.co/api/v2/version/24/", "name": "y"}, "flavor_text": "\u305f\u305f\u304b\u3044\u3067\u3000\u30df\u30ce\u304c\u3000\u3053\u308f\u308c\u3066\u3057\u307e\u3046\u3068\n\u3061\u304b\u304f\u306b\u3042\u308b\u3000\u3056\u3044\u308a\u3087\u3046\u3067\n\u30df\u30ce\u3092\u3000\u3059\u3050\u306b\u3000\u3064\u304f\u308a\u306a\u304a\u3059\u3002"}, {"language": {"url": "https://pokeapi.co/api/v2/language/11/", "name": "ja-kanji"}, "version": {"url": "https://pokeapi.co/api/v2/version/23/", "name": "x"}, "flavor_text": "\u51b7\u305f\u3044\u3000\u6728\u67af\u3089\u3057\u3092\u3000\u9632\u3050\u305f\u3081\n\u5c0f\u679d\u3084\u3000\u843d\u3061\u8449\u3092\u3000\u6750\u6599\u306b\n\u30df\u30ce\u3092\u3000\u4f5c\u308a\u3000\u4f53\u3092\u3000\u8986\u3046\u3002"}, {"language": {"url": "https://pokeapi.co/api/v2/language/9/", "name": "en"}, "version": {"url": "https://pokeapi.co/api/v2/version/23/", "name": "x"}, "flavor_text": "To shelter itself from cold, wintry winds, it covers\nitself with a cloak made of twigs and leaves."}, {"language": {"url": "https://pokeapi.co/api/v2/language/8/", "name": "it"}, "version": {"url": "https://pokeapi.co/api/v2/version/23/", "name": "x"}, "flavor_text": "Per ripararsi dal freddo e dai venti invernali si copre\ncon un manto fatto di rami e foglie."}, {"language": {"url": "https://pokeapi.co/api/v2/language/7/", "name": "es"}, "version": {"url": "https://pokeapi.co/api/v2/version/23/", "name": "x"}, "flavor_text": "Para protegerse de los vientos fr\u00edos invernales, se\ncubre con un caparaz\u00f3n de ramas y hojas."}, {"language": {"url": "https://pokeapi.co/api/v2/language/6/", "name": "de"}, "version": {"url": "https://pokeapi.co/api/v2/version/23/", "name": "x"}, "flavor_text": "Um sich vor dem eisigen Winterwind zu sch\u00fctzen,\nlegt es sich unter einen Umhang aus \u00c4sten und Laub."}, {"language": {"url": "https://pokeapi.co/api/v2/language/5/", "name": "fr"}, "version": {"url": "https://pokeapi.co/api/v2/version/23/", "name": "x"}, "flavor_text": "Pour se prot\u00e9ger des vents glac\u00e9s de l\u2019hiver, il s\u2019est\ntiss\u00e9 une cape de feuilles et de brindilles."}, {"language": {"url": "https://pokeapi.co/api/v2/language/3/", "name": "ko"}, "version": {"url": "https://pokeapi.co/api/v2/version/23/", "name": "x"}, "flavor_text": "\ucc28\uac00\uc6b4 \ucd08\uaca8\uc6b8 \ubc14\ub78c\uc744 \ub9c9\uc73c\ub824\uace0\n\uc791\uc740 \uac00\uc9c0\ub098 \ub099\uc5fd\uc744 \uc7ac\ub8cc\ub85c\n\ub3c4\ub871\uc774\ub97c \ub9cc\ub4e4\uc5b4 \ubab8\uc744 \uac10\uc2fc\ub2e4."}, {"language": {"url": "https://pokeapi.co/api/v2/language/1/", "name": "ja"}, "version": {"url": "https://pokeapi.co/api/v2/version/23/", "name": "x"}, "flavor_text": "\u3064\u3081\u305f\u3044\u3000\u3053\u304c\u3089\u3057\u3092\u3000\u3075\u305b\u3050\u305f\u3081\n\u3053\u3048\u3060\u3084\u3000\u304a\u3061\u3070\u3092\u3000\u3056\u3044\u308a\u3087\u3046\u306b\n\u30df\u30ce\u3092\u3000\u3064\u304f\u308a\u3000\u304b\u3089\u3060\u3092\u3000\u304a\u304a\u3046\u3002"}, {"language": {"url": "https://pokeapi.co/api/v2/language/9/", "name": "en"}, "version": {"url": "https://pokeapi.co/api/v2/version/22/", "name": "white-2"}, "flavor_text": "Even if it is born where there are\nno cocooning materials, it somehow\nalways ends up with a cloak."}, {"language": {"url": "https://pokeapi.co/api/v2/language/9/", "name": "en"}, "version": {"url": "https://pokeapi.co/api/v2/version/21/", "name": "black-2"}, "flavor_text": "Even if it is born where there are\nno cocooning materials, it somehow\nalways ends up with a cloak."}, {"language": {"url": "https://pokeapi.co/api/v2/language/9/", "name": "en"}, "version": {"url": "https://pokeapi.co/api/v2/version/18/", "name": "white"}, "flavor_text": "Even if it is born where there are\nno cocooning materials, it somehow\nalways ends up with a cloak."}, {"language": {"url": "https://pokeapi.co/api/v2/language/5/", "name": "fr"}, "version": {"url": "https://pokeapi.co/api/v2/version/18/", "name": "white"}, "flavor_text": "Nul ne sait comment il y parvient,\nmais il arrive toujours \u00e0 se former\nune cape, o\u00f9 qu\u2019il soit."}, {"language": {"url": "https://pokeapi.co/api/v2/language/9/", "name": "en"}, "version": {"url": "https://pokeapi.co/api/v2/version/17/", "name": "black"}, "flavor_text": "Even if it is born where there are\nno cocooning materials, it somehow\nalways ends up with a cloak."}, {"language": {"url": "https://pokeapi.co/api/v2/language/5/", "name": "fr"}, "version": {"url": "https://pokeapi.co/api/v2/version/17/", "name": "black"}, "flavor_text": "Nul ne sait comment il y parvient,\nmais il arrive toujours \u00e0 se former\nune cape, o\u00f9 qu\u2019il soit."}, {"language": {"url": "https://pokeapi.co/api/v2/language/9/", "name": "en"}, "version": {"url": "https://pokeapi.co/api/v2/version/16/", "name": "soulsilver"}, "flavor_text": "It covers itself with a cloak to\nshelter from the cold. When it\u2019s\nhot, its cloak is thinner."}, {"language": {"url": "https://pokeapi.co/api/v2/language/9/", "name": "en"}, "version": {"url": "https://pokeapi.co/api/v2/version/15/", "name": "heartgold"}, "flavor_text": "It covers itself with a cloak to\nshelter from the cold. When it\u2019s\nhot, its cloak is thinner."}, {"language": {"url": "https://pokeapi.co/api/v2/language/9/", "name": "en"}, "version": {"url": "https://pokeapi.co/api/v2/version/14/", "name": "platinum"}, "flavor_text": "Even if it is born where there are\nno cocooning materials, it somehow\nalways ends up with a cloak."}, {"language": {"url": "https://pokeapi.co/api/v2/language/9/", "name": "en"}, "version": {"url": "https://pokeapi.co/api/v2/version/13/", "name": "pearl"}, "flavor_text": "If its cloak is broken in battle,\nit quickly remakes the cloak with\nmaterials nearby."}, {"language": {"url": "https://pokeapi.co/api/v2/language/9/", "name": "en"}, "version": {"url": "https://pokeapi.co/api/v2/version/12/", "name": "diamond"}, "flavor_text": "To shelter itself from cold, wintry\nwinds, it covers itself with a cloak\nmade of twigs and leaves."}], "name": "burmy", "genera": [{"language": {"url": "https://pokeapi.co/api/v2/language/9/", "name": "en"}, "genus": "Bagworm"}, {"language": {"url": "https://pokeapi.co/api/v2/language/8/", "name": "it"}, "genus": "Larva"}, {"language": {"url": "https://pokeapi.co/api/v2/language/7/", "name": "es"}, "genus": "Larva"}, {"language": {"url": "https://pokeapi.co/api/v2/language/6/", "name": "de"}, "genus": "Beutelwurm"}, {"language": {"url": "https://pokeapi.co/api/v2/language/5/", "name": "fr"}, "genus": "Ver Cach\u00e9"}, {"language": {"url": "https://pokeapi.co/api/v2/language/3/", "name": "ko"}, "genus": "\ub3c4\ub871\uc774\ubc8c\ub808"}, {"language": {"url": "https://pokeapi.co/api/v2/language/1/", "name": "ja"}, "genus": "\u307f\u306e\u3080\u3057"}], "base_happiness": 70, "capture_rate": 120, "growth_rate": {"url": "https://pokeapi.co/api/v2/growth-rate/2/", "name": "medium"}, "names": [{"language": {"url": "https://pokeapi.co/api/v2/language/9/", "name": "en"}, "name": "Burmy"}, {"language": {"url": "https://pokeapi.co/api/v2/language/8/", "name": "it"}, "name": "Burmy"}, {"language": {"url": "https://pokeapi.co/api/v2/language/7/", "name": "es"}, "name": "Burmy"}, {"language": {"url": "https://pokeapi.co/api/v2/language/6/", "name": "de"}, "name": "Burmy"}, {"language": {"url": "https://pokeapi.co/api/v2/language/5/", "name": "fr"}, "name": "Cheniti"}, {"language": {"url": "https://pokeapi.co/api/v2/language/4/", "name": "zh"}, "name": "\u7d50\u8349\u5152"}, {"language": {"url": "https://pokeapi.co/api/v2/language/3/", "name": "ko"}, "name": "\ub3c4\ub871\ucda9\uc774"}, {"language": {"url": "https://pokeapi.co/api/v2/language/2/", "name": "roomaji"}, "name": "Minomucchi"}, {"language": {"url": "https://pokeapi.co/api/v2/language/1/", "name": "ja"}, "name": "\u30df\u30ce\u30e0\u30c3\u30c1"}], "hatch_counter": 15, "habitat": null, "id": 412, "egg_groups": [{"url": "https://pokeapi.co/api/v2/egg-group/3/", "name": "bug"}], "forms_switchable": true, "generation": {"url": "https://pokeapi.co/api/v2/generation/4/", "name": "generation-iv"}, "gender_rate": 4, "evolves_from_species": null, "order": 440}}